{
    "version": "2018.3",
    "homepage": "https://www.jetbrains.com/go/",
    "url": "https://download.jetbrains.com/go/goland-2018.3.exe#/dl.7z",
    "hash": "0e295e77f0f620aea43492fcab13b40d40f3b7e0cf4a994e9a1a83aeac5a92a2",
    "env_add_path": "bin",
    "notes": "Please restart your command line for changes to take effect.",
    "architecture": {
        "64bit": {
            "bin": [
                [
                    "bin\\goland64.exe",
                    "goland"
                ]
            ],
            "shortcuts": [
                [
                    "bin/goland64.exe",
                    "GoLand64"
                ]
            ]
        },
        "32bit": {
            "bin": [
                [
                    "bin\\goland.exe",
                    "goland"
                ]
            ],
            "shortcuts": [
                [
                    "bin/goland.exe",
                    "GoLand"
                ]
            ]
        }
    },
    "checkver": {
        "url": "https://data.services.jetbrains.com/products/releases?code=GO&latest=true&type=release",
        "jp": "$..version"
    },
    "autoupdate": {
        "url": "https://download.jetbrains.com/go/goland-$version.exe#/dl.7z",
        "hash": {
            "url": "https://download.jetbrains.com/go/goland-$version.exe.sha256"
        }
    }
}
