{
    "version": "2020.1.1",
    "homepage": "https://www.jetbrains.com/go/",
    "url": "https://download.jetbrains.com/go/goland-2020.1.1.exe#/dl.7z",
    "hash": "87ea2df8dff6799791d038d13c1ad53d7be35ac9f55a0bad3b232220cdadd190",
    "env_add_path": "bin",
    "notes": "Please restart your command line for changes to take effect.",
    "architecture": {
        "64bit": {
            "bin": [
                [
                    "bin\\goland64.exe",
                    "goland"
                ]
            ],
            "shortcuts": [
                [
                    "bin/goland64.exe",
                    "GoLand64"
                ]
            ]
        },
        "32bit": {
            "bin": [
                [
                    "bin\\goland.exe",
                    "goland"
                ]
            ],
            "shortcuts": [
                [
                    "bin/goland.exe",
                    "GoLand"
                ]
            ]
        }
    },
    "checkver": {
        "url": "https://data.services.jetbrains.com/products/releases?code=GO&latest=true&type=release",
        "jp": "$..version"
    },
    "autoupdate": {
        "url": "https://download.jetbrains.com/go/goland-$version.exe#/dl.7z",
        "hash": {
            "url": "https://download.jetbrains.com/go/goland-$version.exe.sha256"
        }
    }
}
